edgeauth/__init__.py
edgeauth/cli.py
edgeauth/digest_tokens.py
edgeauth/token_builder.py
phenix_edge_auth-1.2.6.dist-info/METADATA
phenix_edge_auth-1.2.6.dist-info/WHEEL
phenix_edge_auth-1.2.6.dist-info/entry_points.txt
phenix_edge_auth-1.2.6.dist-info/top_level.txt
phenix_edge_auth-1.2.6.dist-info/RECORD
