Metadata-Version: 2.1
Name: phenix-edge-auth
Version: 1.2.6
Summary: Easily generate secure digest tokens to use with the Phenix platform
Home-page: https://github.com/PhenixRTS/EdgeAuth/python
Author: Tim Gronkowski, Brandon Drake
Author-email: tim.gronkowski@phenixrts.com
License: Apache-2.0
Platform: UNKNOWN
Classifier: Programming Language :: Python :: 3
Classifier: License :: OSI Approved :: Apache Software License
Classifier: Operating System :: OS Independent
Requires-Python: >=3.6
